[
null,
{"id":1,"actions":[{"conditionParam1":0,"conditionParam2":0,"conditionType":0,"rating":5,"skillId":3}],"battlerHue":0,"battlerName":"nota","dropItems":[{"dataId":1,"denominator":1,"kind":0},{"dataId":1,"denominator":1,"kind":0},{"dataId":1,"denominator":1,"kind":0}],"exp":0,"traits":[{"code":22,"dataId":0,"value":0.95},{"code":22,"dataId":1,"value":0.05},{"code":31,"dataId":1,"value":0}],"gold":0,"name":"Errante","note":"","params":[300,0,30,250,30,30,30,30]},
{"id":2,"actions":[{"conditionParam1":0,"conditionParam2":0,"conditionType":0,"rating":5,"skillId":3}],"battlerHue":0,"battlerName":"nota 2","dropItems":[{"dataId":1,"denominator":1,"kind":0},{"dataId":1,"denominator":1,"kind":0},{"dataId":1,"denominator":1,"kind":0}],"exp":0,"traits":[{"code":22,"dataId":0,"value":0.95},{"code":22,"dataId":1,"value":0.05},{"code":31,"dataId":1,"value":0}],"gold":0,"name":"Errante","note":"","params":[350,0,30,200,30,30,30,30]},
{"id":3,"actions":[{"conditionParam1":0,"conditionParam2":0,"conditionType":0,"rating":5,"skillId":3}],"battlerHue":303,"battlerName":"nota","dropItems":[{"dataId":1,"denominator":1,"kind":0},{"dataId":1,"denominator":1,"kind":0},{"dataId":1,"denominator":1,"kind":0}],"exp":0,"traits":[{"code":22,"dataId":0,"value":0.95},{"code":22,"dataId":1,"value":0.05},{"code":31,"dataId":1,"value":0}],"gold":0,"name":"Errante Mejorado","note":"","params":[400,0,30,200,30,30,30,30]},
{"id":4,"actions":[{"conditionParam1":0,"conditionParam2":0,"conditionType":0,"rating":5,"skillId":8},{"conditionParam1":0,"conditionParam2":0,"conditionType":0,"rating":5,"skillId":9}],"battlerHue":0,"battlerName":"Robot1","dropItems":[{"dataId":1,"denominator":1,"kind":0},{"dataId":1,"denominator":1,"kind":0},{"dataId":1,"denominator":1,"kind":0}],"exp":0,"traits":[{"code":22,"dataId":0,"value":0.95},{"code":22,"dataId":1,"value":0.05},{"code":31,"dataId":1,"value":0}],"gold":0,"name":"Robot 1","note":"","params":[400,0,200,85,10,10,40,35]},
{"id":5,"actions":[{"conditionParam1":0,"conditionParam2":0,"conditionType":0,"rating":5,"skillId":5}],"battlerHue":0,"battlerName":"robot3","dropItems":[{"dataId":1,"denominator":1,"kind":0},{"dataId":1,"denominator":1,"kind":0},{"dataId":1,"denominator":1,"kind":0}],"exp":0,"traits":[{"code":22,"dataId":0,"value":0.95},{"code":22,"dataId":1,"value":0.05},{"code":31,"dataId":1,"value":0}],"gold":0,"name":"Robot 3","note":"","params":[200,0,70,50,10,10,10,25]},
{"id":6,"actions":[{"conditionParam1":0,"conditionParam2":0,"conditionType":0,"rating":5,"skillId":6},{"conditionParam1":0,"conditionParam2":0,"conditionType":0,"rating":5,"skillId":7}],"battlerHue":0,"battlerName":"Robot4","dropItems":[{"dataId":1,"denominator":1,"kind":0},{"dataId":1,"denominator":1,"kind":0},{"dataId":1,"denominator":1,"kind":0}],"exp":0,"traits":[{"code":22,"dataId":0,"value":0.95},{"code":22,"dataId":1,"value":0.05},{"code":31,"dataId":1,"value":0}],"gold":0,"name":"Robot 4","note":"","params":[1600,0,350,125,10,10,100,50]},
{"id":7,"actions":[{"conditionParam1":0,"conditionParam2":0,"conditionType":0,"rating":5,"skillId":13},{"conditionParam1":0,"conditionParam2":0,"conditionType":0,"rating":5,"skillId":11},{"conditionParam1":0,"conditionParam2":0,"conditionType":0,"rating":5,"skillId":12}],"battlerHue":0,"battlerName":"Robot5","dropItems":[{"dataId":1,"denominator":1,"kind":0},{"dataId":1,"denominator":1,"kind":0},{"dataId":1,"denominator":1,"kind":0}],"exp":0,"traits":[{"code":22,"dataId":0,"value":0.95},{"code":22,"dataId":1,"value":0.05},{"code":31,"dataId":1,"value":0}],"gold":0,"name":"Robot 5","note":"","params":[3000,0,500,75,10,10,50,50]},
{"id":8,"actions":[{"conditionParam1":0,"conditionParam2":0,"conditionType":0,"rating":5,"skillId":10}],"battlerHue":0,"battlerName":"Robot6","dropItems":[{"dataId":1,"denominator":1,"kind":0},{"dataId":1,"denominator":1,"kind":0},{"dataId":1,"denominator":1,"kind":0}],"exp":0,"traits":[{"code":22,"dataId":0,"value":0.95},{"code":22,"dataId":1,"value":0.05},{"code":31,"dataId":1,"value":0}],"gold":0,"name":"Robot 6","note":"","params":[200,0,250,50,10,10,5,5]},
{"id":9,"actions":[{"conditionParam1":0,"conditionParam2":0,"conditionType":0,"rating":5,"skillId":14},{"conditionParam1":0,"conditionParam2":0,"conditionType":0,"rating":5,"skillId":15}],"battlerHue":0,"battlerName":"Robot7","dropItems":[{"dataId":1,"denominator":1,"kind":0},{"dataId":1,"denominator":1,"kind":0},{"dataId":1,"denominator":1,"kind":0}],"exp":0,"traits":[{"code":22,"dataId":0,"value":0.95},{"code":22,"dataId":1,"value":0.05},{"code":31,"dataId":1,"value":0}],"gold":0,"name":"Robot 7","note":"","params":[800,0,280,95,10,10,50,50]},
{"id":10,"actions":[{"conditionParam1":0,"conditionParam2":0,"conditionType":0,"rating":5,"skillId":4},{"conditionParam1":0,"conditionParam2":0,"conditionType":0,"rating":5,"skillId":16},{"conditionParam1":0,"conditionParam2":0,"conditionType":0,"rating":5,"skillId":11},{"conditionParam1":0,"conditionParam2":0,"conditionType":0,"rating":5,"skillId":12}],"battlerHue":0,"battlerName":"Actor1_3","dropItems":[{"dataId":1,"denominator":1,"kind":0},{"dataId":1,"denominator":1,"kind":0},{"dataId":1,"denominator":1,"kind":0}],"exp":0,"traits":[{"code":22,"dataId":0,"value":0.95},{"code":22,"dataId":1,"value":0.05},{"code":31,"dataId":1,"value":0}],"gold":0,"name":"Preboss","note":"<Sideview Battler: Mecha-Suit-SV-Battler>","params":[5000,1000,550,150,100,100,50,50]},
{"id":11,"actions":[{"conditionParam1":0,"conditionParam2":0,"conditionType":0,"rating":5,"skillId":17},{"conditionParam1":0,"conditionParam2":0,"conditionType":0,"rating":5,"skillId":18},{"conditionParam1":0,"conditionParam2":0,"conditionType":0,"rating":5,"skillId":21},{"conditionParam1":0,"conditionParam2":0,"conditionType":0,"rating":5,"skillId":23}],"battlerHue":0,"battlerName":"Irongiant","dropItems":[{"dataId":1,"denominator":1,"kind":0},{"dataId":1,"denominator":1,"kind":0},{"dataId":1,"denominator":1,"kind":0}],"exp":0,"traits":[{"code":22,"dataId":0,"value":0.95},{"code":22,"dataId":1,"value":0.05},{"code":31,"dataId":1,"value":0}],"gold":0,"name":"D.E 060799","note":"<Sideview Battler: IronGiant>","params":[5000,10,650,200,10,10,100,50]},
{"id":12,"actions":[{"conditionParam1":0,"conditionParam2":0,"conditionType":0,"rating":5,"skillId":13},{"conditionParam1":0,"conditionParam2":0,"conditionType":0,"rating":5,"skillId":11},{"conditionParam1":0,"conditionParam2":0,"conditionType":0,"rating":5,"skillId":12}],"battlerHue":0,"battlerName":"Robot Elite","dropItems":[{"dataId":1,"denominator":1,"kind":0},{"dataId":1,"denominator":1,"kind":0},{"dataId":1,"denominator":1,"kind":0}],"exp":0,"traits":[{"code":22,"dataId":0,"value":0.95},{"code":22,"dataId":1,"value":0.05},{"code":31,"dataId":1,"value":0}],"gold":0,"name":"Robot Elite","note":"","params":[3250,0,500,125,10,10,40,30]},
{"id":13,"actions":[{"conditionParam1":0,"conditionParam2":0,"conditionType":0,"rating":5,"skillId":17},{"conditionParam1":0,"conditionParam2":0,"conditionType":0,"rating":5,"skillId":18},{"conditionParam1":0,"conditionParam2":0,"conditionType":0,"rating":5,"skillId":19},{"conditionParam1":0,"conditionParam2":0,"conditionType":0,"rating":5,"skillId":20},{"conditionParam1":0,"conditionParam2":0,"conditionType":0,"rating":5,"skillId":21},{"conditionParam1":0,"conditionParam2":0,"conditionType":0,"rating":5,"skillId":22},{"conditionParam1":0,"conditionParam2":0,"conditionType":0,"rating":5,"skillId":23}],"battlerHue":0,"battlerName":"Irongiant","dropItems":[{"dataId":1,"denominator":1,"kind":0},{"dataId":1,"denominator":1,"kind":0},{"dataId":1,"denominator":1,"kind":0}],"exp":0,"traits":[{"code":22,"dataId":0,"value":0.95},{"code":22,"dataId":1,"value":0.05},{"code":31,"dataId":1,"value":0},{"code":61,"dataId":0,"value":0.1},{"code":34,"dataId":0,"value":2},{"code":22,"dataId":7,"value":0.01}],"gold":0,"name":"D.E 060799","note":"<Sideview Battler: IronGiant>","params":[15000,10,650,200,10,10,100,50]},
{"id":14,"actions":[{"conditionParam1":0,"conditionParam2":0,"conditionType":0,"rating":5,"skillId":1}],"battlerHue":0,"battlerName":"","dropItems":[{"dataId":1,"denominator":1,"kind":0},{"dataId":1,"denominator":1,"kind":0},{"dataId":1,"denominator":1,"kind":0}],"exp":0,"traits":[{"code":22,"dataId":0,"value":0.95},{"code":22,"dataId":1,"value":0.05},{"code":31,"dataId":1,"value":0}],"gold":0,"name":"","note":"","params":[100,0,10,10,10,10,10,10]}
]